CHANGES.md
MANIFEST.in
README.md
setup.py
django_terra_geocrud.egg-info/PKG-INFO
django_terra_geocrud.egg-info/SOURCES.txt
django_terra_geocrud.egg-info/dependency_links.txt
django_terra_geocrud.egg-info/requires.txt
django_terra_geocrud.egg-info/top_level.txt
terra_geocrud/VERSION.md
terra_geocrud/__init__.py
terra_geocrud/admin.py
terra_geocrud/apps.py
terra_geocrud/forms.py
terra_geocrud/models.py
terra_geocrud/serializers.py
terra_geocrud/settings.py
terra_geocrud/signals.py
terra_geocrud/tasks.py
terra_geocrud/thumbnail_backends.py
terra_geocrud/urls.py
terra_geocrud/validators.py
terra_geocrud/views.py
terra_geocrud/locale/en/LC_MESSAGES/django.mo
terra_geocrud/locale/en/LC_MESSAGES/django.po
terra_geocrud/locale/fr/LC_MESSAGES/django.mo
terra_geocrud/locale/fr/LC_MESSAGES/django.po
terra_geocrud/management/__init__.py
terra_geocrud/management/commands/__init__.py
terra_geocrud/management/commands/cleanup_properties_files.py
terra_geocrud/management/commands/create_default_crud_views.py
terra_geocrud/map/__init__.py
terra_geocrud/map/styles.py
terra_geocrud/migrations/0001_initial.py
terra_geocrud/migrations/0002_auto_20190723_1156.py
terra_geocrud/migrations/0003_auto_20190724_0849.py
terra_geocrud/migrations/0004_auto_20190724_0906.py
terra_geocrud/migrations/0005_auto_20190724_1435.py
terra_geocrud/migrations/0006_auto_20190725_0830.py
terra_geocrud/migrations/0007_auto_20190725_1256.py
terra_geocrud/migrations/0008_crudview_template.py
terra_geocrud/migrations/0009_auto_20190830_1018.py
terra_geocrud/migrations/0010_auto_20190830_1259.py
terra_geocrud/migrations/0011_auto_20190902_0830.py
terra_geocrud/migrations/0012_auto_20190913_1303.py
terra_geocrud/migrations/0013_featurepropertydisplaygroup.py
terra_geocrud/migrations/0014_auto_20190927_1226.py
terra_geocrud/migrations/0015_auto_20190927_1230.py
terra_geocrud/migrations/0016_auto_20190927_1231.py
terra_geocrud/migrations/0017_featurepropertydisplaygroup_order.py
terra_geocrud/migrations/0018_auto_20190927_1335.py
terra_geocrud/migrations/0019_auto_20190927_1349.py
terra_geocrud/migrations/0020_auto_20190927_1430.py
terra_geocrud/migrations/0021_auto_20190928_1047.py
